bytedance_fornax_user_case/__init__.py
bytedance_fornax_user_case-0.0.1.dist-info/METADATA
bytedance_fornax_user_case-0.0.1.dist-info/WHEEL
bytedance_fornax_user_case-0.0.1.dist-info/top_level.txt
bytedance_fornax_user_case-0.0.1.dist-info/RECORD
